zope.deferredimport-5.0-py3.11-nspkg.pth
zope/deferredimport/__init__.py
zope/deferredimport/deferredmodule.py
zope/deferredimport/tests.py
zope/deferredimport/samples/__init__.py
zope/deferredimport/samples/sample1.py
zope/deferredimport/samples/sample2.py
zope/deferredimport/samples/sample5.py
zope/deferredimport/samples/sample6.py
zope/deferredimport/samples/sample7.py
zope/deferredimport/samples/sample8.py
zope/deferredimport/samples/sample9.py
zope.deferredimport-5.0.dist-info/LICENSE.txt
zope.deferredimport-5.0.dist-info/METADATA
zope.deferredimport-5.0.dist-info/WHEEL
zope.deferredimport-5.0.dist-info/namespace_packages.txt
zope.deferredimport-5.0.dist-info/top_level.txt
zope.deferredimport-5.0.dist-info/RECORD
